mycttestsdk/__init__.py
mycttestsdk/run.py
vsvn_application_monitoring-1.0.0.dist-info/LICENSE
vsvn_application_monitoring-1.0.0.dist-info/METADATA
vsvn_application_monitoring-1.0.0.dist-info/WHEEL
vsvn_application_monitoring-1.0.0.dist-info/top_level.txt
vsvn_application_monitoring-1.0.0.dist-info/RECORD
